shaddock/__init__.py
shaddock/checks.py
shaddock/handler.py
shaddock/model.py
shaddock/scheduler.py
shaddock/cli/__init__.py
shaddock/cli/shell.py
shaddock/cli/views.py
shaddock/drivers/__init__.py
shaddock/drivers/docker/__init__.py
shaddock/drivers/docker/api.py
shaddock/drivers/docker/container.py
shaddock/drivers/docker/image.py
shaddock/drivers/docker/networking.py
shaddock/drivers/systemd/__init__.py
shaddock/drivers/systemd/api.py
shaddock/drivers/systemd/scp.py
shaddock/drivers/systemd/service.py
shaddock/drivers/systemd/ssh.py
shaddock-0.6.2.dev4.dist-info/DESCRIPTION.rst
shaddock-0.6.2.dev4.dist-info/METADATA
shaddock-0.6.2.dev4.dist-info/RECORD
shaddock-0.6.2.dev4.dist-info/WHEEL
shaddock-0.6.2.dev4.dist-info/entry_points.txt
shaddock-0.6.2.dev4.dist-info/metadata.json
shaddock-0.6.2.dev4.dist-info/pbr.json
shaddock-0.6.2.dev4.dist-info/top_level.txt
