Metadata-Version: 2.0
Name: shaddock
Version: 0.6.2.dev4
Summary: A container based orchestration and deployment tool
Home-page: http://shaddock.epheo.eu
Author: Thibaut Lapierre
Author-email: shaddock@epheo.eu
License: Apache License, Version 2.0
Platform: UNKNOWN
Classifier: Environment :: OpenStack
Classifier: Development Status :: 4 - Beta
Classifier: Environment :: Console
Classifier: Intended Audience :: Information Technology
Classifier: Intended Audience :: Developers
Classifier: Intended Audience :: System Administrators
Classifier: License :: OSI Approved :: Apache Software License
Classifier: Programming Language :: Python
Classifier: Programming Language :: Python :: 2.7
Classifier: Programming Language :: Python :: 3.6
Classifier: Operating System :: POSIX :: Linux
Requires-Dist: Babel (>=1.3)
Requires-Dist: PyYAML (==3.11)
Requires-Dist: backports.ssl-match-hostname (>=3.5.0.1)
Requires-Dist: cliff (==1.10.1)
Requires-Dist: docker-py (>=1.10.6)
Requires-Dist: future (==0.14.3)
Requires-Dist: jinja2 (==2.8)
Requires-Dist: oslo.config (<3.0,>=1.4.0)
Requires-Dist: pbr (>=1.6)
